cocotb/fle/rtl/fle6.v
// Automatically generated by PRGA's RTL generator
module fle6 (
    // user accessible ports
    input wire [0:0] clk,
    input wire [5:0] bits_in,
    output reg [1:0] out,
    input wire [0:0] cin,
    output reg [0:0] cout,

    // configuartion ports
    input wire [0:0] cfg_clk,
    input wire [0:0] cfg_e,
    input wire [0:0] cfg_we,
    input wire [0:0] cfg_i,
    output wire [0:0] cfg_o,

    // Variables for testbench files
    input wire test_clk
    );

    // 3 modes:
    //  1. LUT6 + optional DFF
    //  2. 2x (LUT5 + optional DFF)
    //  3. 2x LUT => adder => optional DFF for sum & cout_fabric

    localparam LUT5A_DATA_WIDTH = 32;
    localparam LUT5B_DATA_WIDTH = 32;
    localparam MODE_WIDTH = 2;

    localparam MODE_LUT6X1 = 2'd0;
    localparam MODE_LUT5X2 = 2'd1;
    localparam MODE_ARITH = 2'd3;

    localparam LUT5A_DATA = 0;
    localparam LUT5B_DATA = LUT5A_DATA + LUT5A_DATA_WIDTH;
    localparam ENABLE_FFA = LUT5B_DATA + LUT5B_DATA_WIDTH;
    localparam ENABLE_FFB = ENABLE_FFA + 1;
    localparam MODE = ENABLE_FFB + 1;
    localparam CIN_FABRIC = MODE + MODE_WIDTH;
    localparam CFG_BITCOUNT = CIN_FABRIC + 1;

    reg [CFG_BITCOUNT - 1:0] cfg_d;
    reg [5:0] internal_in;
    reg [1:0] internal_lut;
    reg [1:0] internal_ff;



    // synopsys translate_off
    // in case the sensitivity list is never triggered
    initial begin
        internal_in = 6'b0;
        $dumpfile("dump.vcd");
        $dumpvars(1,fle6);
    end
    // synopsys translate_on

    always @* begin
        internal_in = bits_in;

        // synopsys translate_off
        // in simulation, force unconnected LUT input to be zeros
        if (bits_in[0] === 1'bx) begin
            internal_in[0] = 1'b0;
        end
        if (bits_in[1] === 1'bx) begin
            internal_in[1] = 1'b0;
        end
        if (bits_in[2] === 1'bx) begin
            internal_in[2] = 1'b0;
        end
        if (bits_in[3] === 1'bx) begin
            internal_in[3] = 1'b0;
        end
        if (bits_in[4] === 1'bx) begin
            internal_in[4] = 1'b0;
        end
        if (bits_in[5] === 1'bx) begin
            internal_in[5] = 1'b0;
        end
        // synopsys translate_on
    end

    wire [1:0] internal_sum;
    assign internal_sum = internal_lut[0] + internal_lut[1] + (cfg_d[CIN_FABRIC] ? internal_in[5] : cin);

    wire [MODE_WIDTH-1:0] mode;
    assign mode = cfg_d[MODE +: MODE_WIDTH];

    always @(posedge clk) begin
        if (cfg_e) begin
            internal_ff <= 2'b0;
        end else if (mode == MODE_ARITH) begin
            internal_ff <= internal_sum;
        end else if (mode == MODE_LUT6X1) begin
            internal_ff[0] <= internal_in[5] ? internal_lut[1] : internal_lut[0];
            internal_ff[1] <= 1'b0;
        end else begin
            internal_ff <= internal_lut;
        end
    end

    always @* begin
        if (cfg_e) begin    // avoid pre-programming oscillating
            internal_lut = 2'b0;
        end else begin
            case (internal_in[4:0])     // synopsys infer_mux
                5'd0: begin
                    internal_lut[0] = cfg_d[LUT5A_DATA + 0];
                    internal_lut[1] = cfg_d[LUT5B_DATA + 0];
                end
                5'd1: begin
                    internal_lut[0] = cfg_d[LUT5A_DATA + 1];
                    internal_lut[1] = cfg_d[LUT5B_DATA + 1];
                end
                5'd2: begin
                    internal_lut[0] = cfg_d[LUT5A_DATA + 2];
                    internal_lut[1] = cfg_d[LUT5B_DATA + 2];
                end
                5'd3: begin
                    internal_lut[0] = cfg_d[LUT5A_DATA + 3];
                    internal_lut[1] = cfg_d[LUT5B_DATA + 3];
                end
                5'd4: begin
                    internal_lut[0] = cfg_d[LUT5A_DATA + 4];
                    internal_lut[1] = cfg_d[LUT5B_DATA + 4];
                end
                5'd5: begin
                    internal_lut[0] = cfg_d[LUT5A_DATA + 5];
                    internal_lut[1] = cfg_d[LUT5B_DATA + 5];
                end
                5'd6: begin
                    internal_lut[0] = cfg_d[LUT5A_DATA + 6];
                    internal_lut[1] = cfg_d[LUT5B_DATA + 6];
                end
                5'd7: begin
                    internal_lut[0] = cfg_d[LUT5A_DATA + 7];
                    internal_lut[1] = cfg_d[LUT5B_DATA + 7];
                end
                5'd8: begin
                    internal_lut[0] = cfg_d[LUT5A_DATA + 8];
                    internal_lut[1] = cfg_d[LUT5B_DATA + 8];
                end
                5'd9: begin
                    internal_lut[0] = cfg_d[LUT5A_DATA + 9];
                    internal_lut[1] = cfg_d[LUT5B_DATA + 9];
                end
                5'd10: begin
                    internal_lut[0] = cfg_d[LUT5A_DATA + 10];
                    internal_lut[1] = cfg_d[LUT5B_DATA + 10];
                end
                5'd11: begin
                    internal_lut[0] = cfg_d[LUT5A_DATA + 11];
                    internal_lut[1] = cfg_d[LUT5B_DATA + 11];
                end
                5'd12: begin
                    internal_lut[0] = cfg_d[LUT5A_DATA + 12];
                    internal_lut[1] = cfg_d[LUT5B_DATA + 12];
                end
                5'd13: begin
                    internal_lut[0] = cfg_d[LUT5A_DATA + 13];
                    internal_lut[1] = cfg_d[LUT5B_DATA + 13];
                end
                5'd14: begin
                    internal_lut[0] = cfg_d[LUT5A_DATA + 14];
                    internal_lut[1] = cfg_d[LUT5B_DATA + 14];
                end
                5'd15: begin
                    internal_lut[0] = cfg_d[LUT5A_DATA + 15];
                    internal_lut[1] = cfg_d[LUT5B_DATA + 15];
                end
                5'd16: begin
                    internal_lut[0] = cfg_d[LUT5A_DATA + 16];
                    internal_lut[1] = cfg_d[LUT5B_DATA + 16];
                end
                5'd17: begin
                    internal_lut[0] = cfg_d[LUT5A_DATA + 17];
                    internal_lut[1] = cfg_d[LUT5B_DATA + 17];
                end
                5'd18: begin
                    internal_lut[0] = cfg_d[LUT5A_DATA + 18];
                    internal_lut[1] = cfg_d[LUT5B_DATA + 18];
                end
                5'd19: begin
                    internal_lut[0] = cfg_d[LUT5A_DATA + 19];
                    internal_lut[1] = cfg_d[LUT5B_DATA + 19];
                end
                5'd20: begin
                    internal_lut[0] = cfg_d[LUT5A_DATA + 20];
                    internal_lut[1] = cfg_d[LUT5B_DATA + 20];
                end
                5'd21: begin
                    internal_lut[0] = cfg_d[LUT5A_DATA + 21];
                    internal_lut[1] = cfg_d[LUT5B_DATA + 21];
                end
                5'd22: begin
                    internal_lut[0] = cfg_d[LUT5A_DATA + 22];
                    internal_lut[1] = cfg_d[LUT5B_DATA + 22];
                end
                5'd23: begin
                    internal_lut[0] = cfg_d[LUT5A_DATA + 23];
                    internal_lut[1] = cfg_d[LUT5B_DATA + 23];
                end
                5'd24: begin
                    internal_lut[0] = cfg_d[LUT5A_DATA + 24];
                    internal_lut[1] = cfg_d[LUT5B_DATA + 24];
                end
                5'd25: begin
                    internal_lut[0] = cfg_d[LUT5A_DATA + 25];
                    internal_lut[1] = cfg_d[LUT5B_DATA + 25];
                end
                5'd26: begin
                    internal_lut[0] = cfg_d[LUT5A_DATA + 26];
                    internal_lut[1] = cfg_d[LUT5B_DATA + 26];
                end
                5'd27: begin
                    internal_lut[0] = cfg_d[LUT5A_DATA + 27];
                    internal_lut[1] = cfg_d[LUT5B_DATA + 27];
                end
                5'd28: begin
                    internal_lut[0] = cfg_d[LUT5A_DATA + 28];
                    internal_lut[1] = cfg_d[LUT5B_DATA + 28];
                end
                5'd29: begin
                    internal_lut[0] = cfg_d[LUT5A_DATA + 29];
                    internal_lut[1] = cfg_d[LUT5B_DATA + 29];
                end
                5'd30: begin
                    internal_lut[0] = cfg_d[LUT5A_DATA + 30];
                    internal_lut[1] = cfg_d[LUT5B_DATA + 30];
                end
                5'd31: begin
                    internal_lut[0] = cfg_d[LUT5A_DATA + 31];
                    internal_lut[1] = cfg_d[LUT5B_DATA + 31];
                end
            endcase
        end
    end

    always @* begin
        if (cfg_e) begin    // avoid pre-programming oscillating
            out = 2'b0;
            cout = 1'b0;
        end else begin
            out = 2'b0;
            cout = 1'b0;

            case (mode)
                MODE_LUT6X1: begin
                    if (cfg_d[ENABLE_FFA]) begin
                        out[0] = internal_ff[0];
                    end else begin
                        out[0] = internal_in[5] ? internal_lut[1] : internal_lut[0];
                    end
                end
                MODE_LUT5X2: begin
                    if (cfg_d[ENABLE_FFA]) begin
                        out[0] = internal_ff[0];
                    end else begin
                        out[0] = internal_lut[0];
                    end
                    if (cfg_d[ENABLE_FFB]) begin
                        out[1] = internal_ff[1];
                    end else begin
                        out[1] = internal_lut[1];
                    end
                end
                MODE_ARITH: begin
                    if (cfg_d[ENABLE_FFA]) begin
                        out[0] = internal_ff[0];
                    end else begin
                        out[0] = internal_sum[0];
                    end
                    if (cfg_d[ENABLE_FFB]) begin
                        out[1] = internal_ff[1];
                    end else begin
                        out[1] = internal_sum[1];
                    end

                    cout = internal_sum[1];
                end
            endcase
        end
    end

    wire [CFG_BITCOUNT - 1 + 1:0] cfg_d_next;

    always @(posedge cfg_clk) begin
        if (cfg_e && cfg_we) begin
            cfg_d <= cfg_d_next;
        end
    end

    assign cfg_d_next = {cfg_d, cfg_i};
    assign cfg_o = cfg_d_next[CFG_BITCOUNT +: 1];

endmodule

cocotb/fle/cocotb_test/dump.vcd
$date
	Sun Jun 14 20:31:59 2020
$end
$version
	Icarus Verilog
$end
$timescale
	1s
$end
$scope module fle6 $end
$var wire 6 ! bits_in [5:0] $end
$var wire 1 " cfg_clk $end
$var wire 1 # cfg_e $end
$var wire 1 $ cfg_i $end
$var wire 1 % cfg_we $end
$var wire 1 & cin $end
$var wire 1 ' clk $end
$var wire 1 ( test_clk $end
$var wire 2 ) mode [1:0] $end
$var wire 2 * internal_sum [1:0] $end
$var wire 1 + cfg_o $end
$var wire 70 , cfg_d_next [69:0] $end
$var reg 69 - cfg_d [68:0] $end
$var reg 1 . cout $end
$var reg 2 / internal_ff [1:0] $end
$var reg 6 0 internal_in [5:0] $end
$var reg 2 1 internal_lut [1:0] $end
$var reg 2 2 out [1:0] $end
$upscope $end
$enddefinitions $end
#0
$dumpvars
b0 2
b0 1
bz 0
b0 /
0.
bxz -
bxzz ,
x+
bx *
bx )
1(
1'
z&
1%
z$
1#
1"
bz !
$end
#1
bxz1 ,
1$
0(
#2
1(
#3
0(
#4
1(
#5
0"
0'
0(
#6
1(
#7
0(
#8
1(
#9
0(
#10
bxz11 ,
bxz1 -
1"
1'
1(
#11
0(
#12
1(
#13
0(
#14
1(
#15
0"
0'
0(
#16
1(
#17
0(
#18
1(
#19
0(
#20
bxz111 ,
bxz11 -
1"
1'
1(
#21
0(
#22
1(
#23
0(
#24
1(
#25
0"
0'
0(
#26
1(
#27
0(
#28
1(
#29
0(
#30
0$
bxz1110 ,
bxz111 -
1"
1'
1(
#31
0(
#32
1(
#33
0(
#34
1(
#35
0"
0'
0(
#36
1(
#37
0(
#38
1(
#39
0(
#40
1$
bxz11101 ,
bxz1110 -
1"
1'
1(
#41
0(
#42
1(
#43
0(
#44
1(
#45
0"
0'
0(
#46
1(
#47
0(
#48
1(
#49
0(
#50
bxz111011 ,
bxz11101 -
1"
1'
1(
#51
0(
#52
1(
#53
0(
#54
1(
#55
0"
0'
0(
#56
1(
#57
0(
#58
1(
#59
0(
#60
bxz1110111 ,
bxz111011 -
1"
1'
1(
#61
0(
#62
1(
#63
0(
#64
1(
#65
0"
0'
0(
#66
1(
#67
0(
#68
1(
#69
0(
#70
bxz11101111 ,
bxz1110111 -
1"
1'
1(
#71
0(
#72
1(
#73
0(
#74
1(
#75
0"
0'
0(
#76
1(
#77
0(
#78
1(
#79
0(
#80
0$
bxz111011110 ,
bxz11101111 -
1"
1'
1(
#81
0(
#82
1(
#83
0(
#84
1(
#85
0"
0'
0(
#86
1(
#87
0(
#88
1(
#89
0(
#90
bxz1110111100 ,
bxz111011110 -
1"
1'
1(
#91
0(
#92
1(
#93
0(
#94
1(
#95
0"
0'
0(
#96
1(
#97
0(
#98
1(
#99
0(
#100
1$
bxz11101111001 ,
bxz1110111100 -
1"
1'
1(
#101
0(
#102
1(
#103
0(
#104
1(
#105
0"
0'
0(
#106
1(
#107
0(
#108
1(
#109
0(
#110
0$
bxz111011110010 ,
bxz11101111001 -
1"
1'
1(
#111
0(
#112
1(
#113
0(
#114
1(
#115
0"
0'
0(
#116
1(
#117
0(
#118
1(
#119
0(
#120
bxz1110111100100 ,
bxz111011110010 -
1"
1'
1(
#121
0(
#122
1(
#123
0(
#124
1(
#125
0"
0'
0(
#126
1(
#127
0(
#128
1(
#129
0(
#130
1$
bxz11101111001001 ,
bxz1110111100100 -
1"
1'
1(
#131
0(
#132
1(
#133
0(
#134
1(
#135
0"
0'
0(
#136
1(
#137
0(
#138
1(
#139
0(
#140
0$
bxz111011110010010 ,
bxz11101111001001 -
1"
1'
1(
#141
0(
#142
1(
#143
0(
#144
1(
#145
0"
0'
0(
#146
1(
#147
0(
#148
1(
#149
0(
#150
bxz1110111100100100 ,
bxz111011110010010 -
1"
1'
1(
#151
0(
#152
1(
#153
0(
#154
1(
#155
0"
0'
0(
#156
1(
#157
0(
#158
1(
#159
0(
#160
1$
bxz11101111001001001 ,
bxz1110111100100100 -
1"
1'
1(
#161
0(
#162
1(
#163
0(
#164
1(
#165
0"
0'
0(
#166
1(
#167
0(
#168
1(
#169
0(
#170
bxz111011110010010011 ,
bxz11101111001001001 -
1"
1'
1(
#171
0(
#172
1(
#173
0(
#174
1(
#175
0"
0'
0(
#176
1(
#177
0(
#178
1(
#179
0(
#180
bxz1110111100100100111 ,
bxz111011110010010011 -
1"
1'
1(
#181
0(
#182
1(
#183
0(
#184
1(
#185
0"
0'
0(
#186
1(
#187
0(
#188
1(
#189
0(
#190
bxz11101111001001001111 ,
bxz1110111100100100111 -
1"
1'
1(
#191
0(
#192
1(
#193
0(
#194
1(
#195
0"
0'
0(
#196
1(
#197
0(
#198
1(
#199
0(
#200
0$
bxz111011110010010011110 ,
bxz11101111001001001111 -
1"
1'
1(
#201
0(
#202
1(
#203
0(
#204
1(
#205
0"
0'
0(
#206
1(
#207
0(
#208
1(
#209
0(
#210
bxz1110111100100100111100 ,
bxz111011110010010011110 -
1"
1'
1(
#211
0(
#212
1(
#213
0(
#214
1(
#215
0"
0'
0(
#216
1(
#217
0(
#218
1(
#219
0(
#220
1$
bxz11101111001001001111001 ,
bxz1110111100100100111100 -
1"
1'
1(
#221
0(
#222
1(
#223
0(
#224
1(
#225
0"
0'
0(
#226
1(
#227
0(
#228
1(
#229
0(
#230
0$
bxz111011110010010011110010 ,
bxz11101111001001001111001 -
1"
1'
1(
#231
0(
#232
1(
#233
0(
#234
1(
#235
0"
0'
0(
#236
1(
#237
0(
#238
1(
#239
0(
#240
1$
bxz1110111100100100111100101 ,
bxz111011110010010011110010 -
1"
1'
1(
#241
0(
#242
1(
#243
0(
#244
1(
#245
0"
0'
0(
#246
1(
#247
0(
#248
1(
#249
0(
#250
bxz11101111001001001111001011 ,
bxz1110111100100100111100101 -
1"
1'
1(
#251
0(
#252
1(
#253
0(
#254
1(
#255
0"
0'
0(
#256
1(
#257
0(
#258
1(
#259
0(
#260
0$
bxz111011110010010011110010110 ,
bxz11101111001001001111001011 -
1"
1'
1(
#261
0(
#262
1(
#263
0(
#264
1(
#265
0"
0'
0(
#266
1(
#267
0(
#268
1(
#269
0(
#270
bxz1110111100100100111100101100 ,
bxz111011110010010011110010110 -
1"
1'
1(
#271
0(
#272
1(
#273
0(
#274
1(
#275
0"
0'
0(
#276
1(
#277
0(
#278
1(
#279
0(
#280
bxz11101111001001001111001011000 ,
bxz1110111100100100111100101100 -
1"
1'
1(
#281
0(
#282
1(
#283
0(
#284
1(
#285
0"
0'
0(
#286
1(
#287
0(
#288
1(
#289
0(
#290
bxz111011110010010011110010110000 ,
bxz11101111001001001111001011000 -
1"
1'
1(
#291
0(
#292
1(
#293
0(
#294
1(
#295
0"
0'
0(
#296
1(
#297
0(
#298
1(
#299
0(
#300
bxz1110111100100100111100101100000 ,
bxz111011110010010011110010110000 -
1"
1'
1(
#301
0(
#302
1(
#303
0(
#304
1(
#305
0"
0'
0(
#306
1(
#307
0(
#308
1(
#309
0(
#310
1$
bxz11101111001001001111001011000001 ,
bxz1110111100100100111100101100000 -
1"
1'
1(
#311
0(
#312
1(
#313
0(
#314
1(
#315
0"
0'
0(
#316
1(
#317
0(
#318
1(
#319
0(
#320
0$
bxz111011110010010011110010110000010 ,
bxz11101111001001001111001011000001 -
1"
1'
1(
#321
0(
#322
1(
#323
0(
#324
1(
#325
0"
0'
0(
#326
1(
#327
0(
#328
1(
#329
0(
#330
bxz1110111100100100111100101100000100 ,
bxz111011110010010011110010110000010 -
1"
1'
1(
#331
0(
#332
1(
#333
0(
#334
1(
#335
0"
0'
0(
#336
1(
#337
0(
#338
1(
#339
0(
#340
1$
bxz11101111001001001111001011000001001 ,
bxz1110111100100100111100101100000100 -
1"
1'
1(
#341
0(
#342
1(
#343
0(
#344
1(
#345
0"
0'
0(
#346
1(
#347
0(
#348
1(
#349
0(
#350
0$
bxz111011110010010011110010110000010010 ,
bxz11101111001001001111001011000001001 -
1"
1'
1(
#351
0(
#352
1(
#353
0(
#354
1(
#355
0"
0'
0(
#356
1(
#357
0(
#358
1(
#359
0(
#360
1$
bxz1110111100100100111100101100000100101 ,
bxz111011110010010011110010110000010010 -
1"
1'
1(
#361
0(
#362
1(
#363
0(
#364
1(
#365
0"
0'
0(
#366
1(
#367
0(
#368
1(
#369
0(
#370
0$
bxz11101111001001001111001011000001001010 ,
bxz1110111100100100111100101100000100101 -
1"
1'
1(
#371
0(
#372
1(
#373
0(
#374
1(
#375
0"
0'
0(
#376
1(
#377
0(
#378
1(
#379
0(
#380
1$
bxz111011110010010011110010110000010010101 ,
bxz11101111001001001111001011000001001010 -
1"
1'
1(
#381
0(
#382
1(
#383
0(
#384
1(
#385
0"
0'
0(
#386
1(
#387
0(
#388
1(
#389
0(
#390
0$
bxz1110111100100100111100101100000100101010 ,
bxz111011110010010011110010110000010010101 -
1"
1'
1(
#391
0(
#392
1(
#393
0(
#394
1(
#395
0"
0'
0(
#396
1(
#397
0(
#398
1(
#399
0(
#400
bxz11101111001001001111001011000001001010100 ,
bxz1110111100100100111100101100000100101010 -
1"
1'
1(
#401
0(
#402
1(
#403
0(
#404
1(
#405
0"
0'
0(
#406
1(
#407
0(
#408
1(
#409
0(
#410
1$
bxz111011110010010011110010110000010010101001 ,
bxz11101111001001001111001011000001001010100 -
1"
1'
1(
#411
0(
#412
1(
#413
0(
#414
1(
#415
0"
0'
0(
#416
1(
#417
0(
#418
1(
#419
0(
#420
bxz1110111100100100111100101100000100101010011 ,
bxz111011110010010011110010110000010010101001 -
1"
1'
1(
#421
0(
#422
1(
#423
0(
#424
1(
#425
0"
0'
0(
#426
1(
#427
0(
#428
1(
#429
0(
#430
0$
bxz11101111001001001111001011000001001010100110 ,
bxz1110111100100100111100101100000100101010011 -
1"
1'
1(
#431
0(
#432
1(
#433
0(
#434
1(
#435
0"
0'
0(
#436
1(
#437
0(
#438
1(
#439
0(
#440
1$
bxz111011110010010011110010110000010010101001101 ,
bxz11101111001001001111001011000001001010100110 -
1"
1'
1(
#441
0(
#442
1(
#443
0(
#444
1(
#445
0"
0'
0(
#446
1(
#447
0(
#448
1(
#449
0(
#450
0$
bxz1110111100100100111100101100000100101010011010 ,
bxz111011110010010011110010110000010010101001101 -
1"
1'
1(
#451
0(
#452
1(
#453
0(
#454
1(
#455
0"
0'
0(
#456
1(
#457
0(
#458
1(
#459
0(
#460
bxz11101111001001001111001011000001001010100110100 ,
bxz1110111100100100111100101100000100101010011010 -
1"
1'
1(
#461
0(
#462
1(
#463
0(
#464
1(
#465
0"
0'
0(
#466
1(
#467
0(
#468
1(
#469
0(
#470
1$
bxz111011110010010011110010110000010010101001101001 ,
bxz11101111001001001111001011000001001010100110100 -
1"
1'
1(
#471
0(
#472
1(
#473
0(
#474
1(
#475
0"
0'
0(
#476
1(
#477
0(
#478
1(
#479
0(
#480
bxz1110111100100100111100101100000100101010011010011 ,
bxz111011110010010011110010110000010010101001101001 -
1"
1'
1(
#481
0(
#482
1(
#483
0(
#484
1(
#485
0"
0'
0(
#486
1(
#487
0(
#488
1(
#489
0(
#490
0$
bxz11101111001001001111001011000001001010100110100110 ,
bxz1110111100100100111100101100000100101010011010011 -
1"
1'
1(
#491
0(
#492
1(
#493
0(
#494
1(
#495
0"
0'
0(
#496
1(
#497
0(
#498
1(
#499
0(
#500
1$
bxz111011110010010011110010110000010010101001101001101 ,
bxz11101111001001001111001011000001001010100110100110 -
1"
1'
1(
#501
0(
#502
1(
#503
0(
#504
1(
#505
0"
0'
0(
#506
1(
#507
0(
#508
1(
#509
0(
#510
0$
bxz1110111100100100111100101100000100101010011010011010 ,
bxz111011110010010011110010110000010010101001101001101 -
1"
1'
1(
#511
0(
#512
1(
#513
0(
#514
1(
#515
0"
0'
0(
#516
1(
#517
0(
#518
1(
#519
0(
#520
1$
bxz11101111001001001111001011000001001010100110100110101 ,
bxz1110111100100100111100101100000100101010011010011010 -
1"
1'
1(
#521
0(
#522
1(
#523
0(
#524
1(
#525
0"
0'
0(
#526
1(
#527
0(
#528
1(
#529
0(
#530
0$
bxz111011110010010011110010110000010010101001101001101010 ,
bxz11101111001001001111001011000001001010100110100110101 -
1"
1'
1(
#531
0(
#532
1(
#533
0(
#534
1(
#535
0"
0'
0(
#536
1(
#537
0(
#538
1(
#539
0(
#540
bxz1110111100100100111100101100000100101010011010011010100 ,
bxz111011110010010011110010110000010010101001101001101010 -
1"
1'
1(
#541
0(
#542
1(
#543
0(
#544
1(
#545
0"
0'
0(
#546
1(
#547
0(
#548
1(
#549
0(
#550
bxz11101111001001001111001011000001001010100110100110101000 ,
bxz1110111100100100111100101100000100101010011010011010100 -
1"
1'
1(
#551
0(
#552
1(
#553
0(
#554
1(
#555
0"
0'
0(
#556
1(
#557
0(
#558
1(
#559
0(
#560
1$
bxz111011110010010011110010110000010010101001101001101010001 ,
bxz11101111001001001111001011000001001010100110100110101000 -
1"
1'
1(
#561
0(
#562
1(
#563
0(
#564
1(
#565
0"
0'
0(
#566
1(
#567
0(
#568
1(
#569
0(
#570
0$
bxz1110111100100100111100101100000100101010011010011010100010 ,
bxz111011110010010011110010110000010010101001101001101010001 -
1"
1'
1(
#571
0(
#572
1(
#573
0(
#574
1(
#575
0"
0'
0(
#576
1(
#577
0(
#578
1(
#579
0(
#580
1$
bxz11101111001001001111001011000001001010100110100110101000101 ,
bxz1110111100100100111100101100000100101010011010011010100010 -
1"
1'
1(
#581
0(
#582
1(
#583
0(
#584
1(
#585
0"
0'
0(
#586
1(
#587
0(
#588
1(
#589
0(
#590
bxz111011110010010011110010110000010010101001101001101010001011 ,
bxz11101111001001001111001011000001001010100110100110101000101 -
1"
1'
1(
#591
0(
#592
1(
#593
0(
#594
1(
#595
0"
0'
0(
#596
1(
#597
0(
#598
1(
#599
0(
#600
0$
bxz1110111100100100111100101100000100101010011010011010100010110 ,
bxz111011110010010011110010110000010010101001101001101010001011 -
1"
1'
1(
#601
0(
#602
1(
#603
0(
#604
1(
#605
0"
0'
0(
#606
1(
#607
0(
#608
1(
#609
0(
#610
1$
bxz11101111001001001111001011000001001010100110100110101000101101 ,
bxz1110111100100100111100101100000100101010011010011010100010110 -
1"
1'
1(
#611
0(
#612
1(
#613
0(
#614
1(
#615
0"
0'
0(
#616
1(
#617
0(
#618
1(
#619
0(
#620
bxz111011110010010011110010110000010010101001101001101010001011011 ,
bxz11101111001001001111001011000001001010100110100110101000101101 -
1"
1'
1(
#621
0(
#622
1(
#623
0(
#624
1(
#625
0"
0'
0(
#626
1(
#627
0(
#628
1(
#629
0(
#630
0$
bxz1110111100100100111100101100000100101010011010011010100010110110 ,
bxz111011110010010011110010110000010010101001101001101010001011011 -
1"
1'
1(
#631
0(
#632
1(
#633
0(
#634
1(
#635
0"
0'
0(
#636
1(
#637
0(
#638
1(
#639
0(
#640
bxz11101111001001001111001011000001001010100110100110101000101101100 ,
bxz1110111100100100111100101100000100101010011010011010100010110110 -
1"
1'
1(
#641
0(
#642
1(
#643
0(
#644
1(
#645
0"
0'
0(
#646
1(
#647
0(
#648
1(
#649
0(
#650
1$
bxz111011110010010011110010110000010010101001101001101010001011011001 ,
bxz11101111001001001111001011000001001010100110100110101000101101100 -
1"
1'
1(
#651
0(
#652
1(
#653
0(
#654
1(
#655
0"
0'
0(
#656
1(
#657
0(
#658
1(
#659
0(
#660
0$
bxz )
bxz1110111100100100111100101100000100101010011010011010100010110110010 ,
bxz111011110010010011110010110000010010101001101001101010001011011001 -
1"
1'
1(
#661
0(
#662
1(
#663
0(
#664
1(
#665
0"
0'
0(
#666
1(
#667
0(
#668
1(
#669
0(
#670
bz1 )
bxz11101111001001001111001011000001001010100110100110101000101101100100 ,
bxz1110111100100100111100101100000100101010011010011010100010110110010 -
1"
1'
1(
#671
0(
#672
1(
#673
0(
#674
1(
#675
0"
0'
0(
#676
1(
#677
0(
#678
1(
#679
0(
#680
1$
b11 )
z+
bz111011110010010011110010110000010010101001101001101010001011011001001 ,
bz11101111001001001111001011000001001010100110100110101000101101100100 -
1"
1'
1(
#681
0(
#682
1(
#683
0(
#684
1(
#685
0"
0'
0(
#686
1(
#687
0(
#688
1(
#689
0(
#690
x.
bx0 2
0#
0%
1+
b1110111100100100111100101100000100101010011010011010100010110110010011 ,
b111011110010010011110010110000010010101001101001101010001011011001001 -
1"
1'
1(
#691
0(
#692
1(
#693
0(
#694
1(
#695
0"
0'
0(
#696
1(
#697
0(
#698
1(
#699
0(
#700
b10 *
b11 1
b0 0
b0 !
1&
1.
b1x 2
bx /
1"
1'
1(
#701
0(
#702
1(
#703
0(
#704
1(
#705
0"
0'
0(
#706
1(
#707
0(
#708
1(
#709
0(
#710
b0 *
b0 1
b1 0
b1 !
0.
b0 2
b10 /
1"
1'
1(
#711
0(
#712
1(
#713
0(
#714
1(
#715
0"
0'
0(
#716
1(
#717
0(
#718
1(
#719
0(
#720
b1 *
b10 1
b10 0
b10 !
b0 /
1"
1'
1(
#721
0(
#722
1(
#723
0(
#724
1(
#725
0"
0'
0(
#726
1(
#727
0(
#728
1(
#729
0(
#730
b1 *
b1 1
b11 0
b11 !
b1 2
b1 /
1"
1'
1(
#731
0(
#732
1(
#733
0(
#734
1(
#735
0"
0'
0(
#736
1(
#737
0(
#738
1(
#739
0(
#740
b0 *
b1 2
b0 1
b100 0
b100 !
1"
1'
1(
#741
0(
#742
1(
#743
0(
#744
1(
#745
0"
0'
0(
#746
1(
#747
0(
#748
1(
#749
0(
#750
b1 *
b10 1
b101 0
b101 !
0&
b0 2
b0 /
1"
1'
1(
#751
0(
#752
1(
#753
0(
#754
1(
#755
0"
0'
0(
#756
1(
#757
0(
#758
1(
#759
0(
#760
b1 *
b1 1
b110 0
b110 !
b1 2
b1 /
1"
1'
1(
#761
0(
#762
1(
#763
0(
#764
1(
#765
0"
0'
0(
#766
1(
#767
0(
#768
1(
#769
0(
#770
b1 2
b111 0
b111 !
1&
1"
1'
1(
#771
0(
#772
1(
#773
0(
#774
1(
#775
0"
0'
0(
#776
1(
#777
0(
#778
1(
#779
0(
#780
b0 *
b1 2
b0 1
b1000 0
b1000 !
0&
1"
1'
1(
#781
0(
#782
1(
#783
0(
#784
1(
#785
0"
0'
0(
#786
1(
#787
0(
#788
1(
#789
0(
#790
b1 *
b1 1
b1001 0
b1001 !
b0 2
b0 /
1"
1'
1(
#791
0(
#792
1(
#793
0(
#794
1(
#795
0"
0'
0(
#796
1(
#797
0(
#798
1(
#799
0(
#800
b1010 0
b1010 !
b1 2
b1 /
1"
1'
1(
#801
0(
#802
1(
#803
0(
#804
1(
#805
0"
0'
0(
#806
1(
#807
0(
#808
1(
#809
0(
#810
b1 *
b1 2
b10 1
b1011 0
b1011 !
1"
1'
1(
#811
0(
#812
1(
#813
0(
#814
1(
#815
0"
0'
0(
#816
1(
#817
0(
#818
1(
#819
0(
#820
1.
b10 *
b11 2
b11 1
b1100 0
b1100 !
1&
1"
1'
1(
#821
0(
#822
1(
#823
0(
#824
1(
#825
0"
0'
0(
#826
1(
#827
0(
#828
1(
#829
0(
#830
b0 *
b0 1
b1101 0
b1101 !
0&
0.
b0 2
b10 /
1"
1'
1(
#831
0(
#832
1(
#833
0(
#834
1(
#835
0"
0'
0(
#836
1(
#837
0(
#838
1(
#839
0(
#840
b1 *
b10 1
b1110 0
b1110 !
1&
b0 /
1"
1'
1(
#841
0(
#842
1(
#843
0(
#844
1(
#845
0"
0'
0(
#846
1(
#847
0(
#848
1(
#849
0(
#850
b0 *
b0 1
b1111 0
b1111 !
b1 2
b1 /
1"
1'
1(
#851
0(
#852
1(
#853
0(
#854
1(
#855
0"
0'
0(
#856
1(
#857
0(
#858
1(
#859
0(
#860
b1 *
b1 1
b10000 0
b10000 !
b0 2
b0 /
1"
1'
1(
#861
0(
#862
1(
#863
0(
#864
1(
#865
0"
0'
0(
#866
1(
#867
0(
#868
1(
#869
0(
#870
b1 *
b10 1
b10001 0
b10001 !
b1 2
b1 /
1"
1'
1(
#871
0(
#872
1(
#873
0(
#874
1(
#875
0"
0'
0(
#876
1(
#877
0(
#878
1(
#879
0(
#880
1.
b10 *
b11 2
b11 1
b10010 0
b10010 !
1"
1'
1(
#881
0(
#882
1(
#883
0(
#884
1(
#885
0"
0'
0(
#886
1(
#887
0(
#888
1(
#889
0(
#890
b1 *
b10 1
b10011 0
b10011 !
0.
b0 2
b10 /
1"
1'
1(
#891
0(
#892
1(
#893
0(
#894
1(
#895
0"
0'
0(
#896
1(
#897
0(
#898
1(
#899
0(
#900
1.
b10 *
b11 1
b10100 0
b10100 !
0&
b11 2
b1 /
1"
1'
1(
#901
0(
#902
1(
#903
0(
#904
1(
#905
0"
0'
0(
#906
1(
#907
0(
#908
1(
#909
0(
