cocotb/lut/rtl/lut4.v
// Automatically generated by PRGA's RTL generator
module lut4 (
    input wire [3:0] bits_in,
    output reg [0:0] out,

    input wire [0:0] cfg_clk,
    input wire [0:0] cfg_e,
    input wire [0:0] cfg_we,
    input wire [0:0] cfg_i,
    output wire [0:0] cfg_o
    );

    reg [15:0] cfg_d;
    reg [3:0] internal_in;
    
    // synopsys translate_off
    // in case the sensitivity list is never triggered
    initial begin
        internal_in = 6'b0;
        $dumpfile("dump.vcd");
        $dumpvars(1,lut4);
    end
    // synopsys translate_on

    always @* begin
        internal_in = bits_in;

        // synopsys translate_off
        // in simulation, force unconnected LUT input to be zeros
        if (bits_in[0] === 1'bx) begin
            internal_in[0] = 1'b0;
        end
        if (bits_in[1] === 1'bx) begin
            internal_in[1] = 1'b0;
        end
        if (bits_in[2] === 1'bx) begin
            internal_in[2] = 1'b0;
        end
        if (bits_in[3] === 1'bx) begin
            internal_in[3] = 1'b0;
        end
        // synopsys translate_on
    end

    always @* begin
        if (cfg_e) begin        // avoid pre-programming oscillating
            out = 1'b0;
        end else begin
            case (internal_in)  // synopsys infer_mux
                4'd0: out = cfg_d[0];
                4'd1: out = cfg_d[1];
                4'd2: out = cfg_d[2];
                4'd3: out = cfg_d[3];
                4'd4: out = cfg_d[4];
                4'd5: out = cfg_d[5];
                4'd6: out = cfg_d[6];
                4'd7: out = cfg_d[7];
                4'd8: out = cfg_d[8];
                4'd9: out = cfg_d[9];
                4'd10: out = cfg_d[10];
                4'd11: out = cfg_d[11];
                4'd12: out = cfg_d[12];
                4'd13: out = cfg_d[13];
                4'd14: out = cfg_d[14];
                4'd15: out = cfg_d[15];
            endcase
        end
    end

    wire [16:0] cfg_d_next;

    always @(posedge cfg_clk) begin
        if (cfg_e && cfg_we) begin
            cfg_d <= cfg_d_next;
        end
    end

    assign cfg_d_next = {cfg_d, cfg_i};
    assign cfg_o = cfg_d_next[16 -: 1];

endmodule

cocotb/lut/cocotb_test/dump.vcd
$date
	Sun Jun 14 19:56:16 2020
$end
$version
	Icarus Verilog
$end
$timescale
	1s
$end
$scope module lut4 $end
$var wire 4 ! bits_in [3:0] $end
$var wire 1 " cfg_clk $end
$var wire 1 # cfg_e $end
$var wire 1 $ cfg_i $end
$var wire 1 % cfg_we $end
$var wire 1 & cfg_o $end
$var wire 17 ' cfg_d_next [16:0] $end
$var reg 16 ( cfg_d [15:0] $end
$var reg 4 ) internal_in [3:0] $end
$var reg 1 * out $end
$upscope $end
$enddefinitions $end
#0
$dumpvars
0*
bz )
bx (
bx1 '
x&
1%
1$
1#
0"
bz !
$end
#5
bx11 '
bx1 (
1"
#10
0"
#15
bx111 '
bx11 (
1"
#20
0"
#25
0$
bx1110 '
bx111 (
1"
#30
0"
#35
1$
bx11101 '
bx1110 (
1"
#40
0"
#45
0$
bx111010 '
bx11101 (
1"
#50
0"
#55
1$
bx1110101 '
bx111010 (
1"
#60
0"
#65
0$
bx11101010 '
bx1110101 (
1"
#70
0"
#75
bx111010100 '
bx11101010 (
1"
#80
0"
#85
bx1110101000 '
bx111010100 (
1"
#90
0"
#95
bx11101010000 '
bx1110101000 (
1"
#100
0"
#105
1$
bx111010100001 '
bx11101010000 (
1"
#110
0"
#115
0$
bx1110101000010 '
bx111010100001 (
1"
#120
0"
#125
bx11101010000100 '
bx1110101000010 (
1"
#130
0"
#135
1$
bx111010100001001 '
bx11101010000100 (
1"
#140
0"
#145
0$
bx1110101000010010 '
bx111010100001001 (
1"
#150
0"
#155
0#
0%
1&
b11101010000100100 '
b1110101000010010 (
1"
#160
0"
#165
b0 )
b0 !
1"
#170
0"
#175
1#
1%
1"
#180
0"
#185
0#
0%
b11010100001001000 '
b1101010000100100 (
1"
#190
0"
#195
b1 )
b1 !
1"
#200
0"
#205
1*
b10 )
b10 !
1"
#210
0"
#215
0*
1#
1%
b11010100001001001 '
1$
1"
#220
0"
#225
0#
0%
b10101000010010011 '
b1010100001001001 (
1"
#230
0"
#235
1*
b11 )
b11 !
1"
#240
0"
#245
0*
1#
1%
b10101000010010010 '
0$
1"
#250
0"
#255
0#
0%
0&
b1010000100100100 '
b101000010010010 (
1"
#260
0"
#265
1*
b100 )
b100 !
1"
#270
0"
#275
0*
b101 )
b101 !
1"
#280
0"
#285
1#
1%
1"
#290
0"
#295
1*
0#
0%
1&
b10100001001001000 '
b1010000100100100 (
1"
#300
0"
#305
0*
b110 )
b110 !
1"
#310
0"
#315
b111 )
b111 !
1"
#320
0"
#325
1*
b1000 )
b1000 !
1"
#330
0"
#335
0*
1#
1%
1"
#340
0"
#345
0#
0%
0&
b1000010010010000 '
b100001001001000 (
1"
#350
0"
#355
1*
b1001 )
b1001 !
1"
#360
0"
#365
0*
b1010 )
b1010 !
1"
#370
0"
#375
b1011 )
b1011 !
1"
#380
0"
#385
1#
1%
b1000010010010001 '
1$
1"
#390
0"
#395
0#
0%
1&
b10000100100100011 '
b1000010010010001 (
1"
#400
0"
#405
b1100 )
b1100 !
1"
#410
0"
#415
1#
1%
b10000100100100010 '
0$
1"
#420
0"
#425
0#
0%
0&
b1001001000100 '
b100100100010 (
1"
#430
0"
#435
b1101 )
b1101 !
1"
#440
0"
#445
1#
1%
1"
#450
0"
#455
0#
0%
b10010010001000 '
b1001001000100 (
1"
#460
0"
#465
b1110 )
b1110 !
1"
#470
0"
#475
1#
1%
b10010010001001 '
1$
1"
#480
0"
#485
0#
0%
b100100100010011 '
b10010010001001 (
1"
#490
0"
#495
b1111 )
b1111 !
1"
#500
0"
#505
1#
1%
1"
#510
0"
#515
0#
0%
b1001001000100111 '
b100100100010011 (
1"
#520
0"
#525
1"
#526
0"
1#
1%
#531
0$
1&
b10010010001001110 '
b1001001000100111 (
1"
#536
0"
#541
0&
b100100010011100 '
b10010001001110 (
1"
#546
0"
#551
b1001000100111000 '
b100100010011100 (
1"
#556
0"
#561
1$
1&
b10010001001110001 '
b1001000100111000 (
1"
#566
0"
#571
0$
0&
b100010011100010 '
b10001001110001 (
1"
#576
0"
#581
b1000100111000100 '
b100010011100010 (
1"
#586
0"
#591
1$
1&
b10001001110001001 '
b1000100111000100 (
1"
#596
0"
#601
0$
0&
b10011100010010 '
b1001110001001 (
1"
#606
0"
#611
b100111000100100 '
b10011100010010 (
1"
#616
0"
#621
b1001110001001000 '
b100111000100100 (
1"
#626
0"
#631
1&
b10011100010010000 '
b1001110001001000 (
1"
#636
0"
#641
0&
b111000100100000 '
b11100010010000 (
1"
#646
0"
#651
b1110001001000000 '
b111000100100000 (
1"
#656
0"
#661
1&
b11100010010000000 '
b1110001001000000 (
1"
#666
0"
#671
b11000100100000000 '
b1100010010000000 (
1"
#676
0"
#681
1*
0#
0%
b10001001000000000 '
b1000100100000000 (
1"
#686
0"
#691
0*
b0 )
b0 !
1"
#696
0"
#701
b1 )
b1 !
1"
#706
0"
#711
b10 )
b10 !
1"
#716
0"
#721
b11 )
b11 !
1"
#726
0"
#731
b100 )
b100 !
1"
#736
0"
#741
b101 )
b101 !
1"
#746
0"
#751
b110 )
b110 !
1"
#756
0"
#761
b111 )
b111 !
1"
#766
0"
#771
1*
b1000 )
b1000 !
1"
#776
0"
#781
0*
b1001 )
b1001 !
1"
#786
0"
#791
b1010 )
b1010 !
1"
#796
0"
#801
1*
b1011 )
b1011 !
1"
#806
0"
#811
0*
b1100 )
b1100 !
1"
#816
0"
#821
b1101 )
b1101 !
1"
#826
0"
#831
b1110 )
b1110 !
1"
#836
0"
#841
1*
b1111 )
b1111 !
1"
