cocotb/fifo_lookahead_to_nonlookahead/fifo_lookahead_buffer.v
// Automatically generated by PRGA's RTL generator
//
// Convert a non-lookahead FIFO to a lookahead FIFO if REVERSED is 0
// or, convert a lookahead FIFO to a non-lookahead FIFO if REVERSED is 1
module fifo_lookahead_buffer #(
    parameter DATA_WIDTH = 32,
    parameter REVERSED = 0
) (
    input wire [0:0] clk,
    input  [0:0] rst,

    input wire [0:0] empty_i,
    output reg [0:0] rd_i,
    input wire [DATA_WIDTH - 1:0] dout_i,

    output reg [0:0] empty,
    input wire [0:0] rd,
    output reg [DATA_WIDTH - 1:0] dout
    );

    generate if (REVERSED) begin
        always @(posedge clk) begin
            dout <= dout_i;
        end

        always @* begin
            empty = empty_i;
            rd_i = rd;
        end
    end else begin
        reg [DATA_WIDTH - 1:0] dout_i_f;
        reg dout_i_valid;

        always @(posedge clk) begin
            if (rst) begin
                empty <= 'b1;
                dout_i_valid <= 'b0;
            end else begin
                if (~empty_i && rd_i) begin
                    empty <= 'b0;
                end else if (rd) begin
                    empty <= 'b1;
                end

                dout_i_valid <= ~empty_i && rd_i;
            end
        end

        always @(posedge clk) begin
            if (dout_i_valid) begin
                dout_i_f <= dout_i;
            end
        end

        always @* begin
            rd_i = empty || rd;
            dout = dout_i_valid ? dout_i : dout_i_f;
        end
    end endgenerate

endmodule

cocotb/fifo_lookahead/ram_1r1w.v
// Automatically generated by PRGA's RTL generator
module ram_1r1w #(
    parameter DATA_WIDTH = 32,
    parameter ADDR_WIDTH = 6,
    parameter RAM_ROWS = 64,
    parameter REGISTER_OUTPUT = 1
) (
    input wire [0:0] clk,

    input wire [ADDR_WIDTH - 1:0] raddr,
    output reg [DATA_WIDTH - 1:0] dout,

    input wire [ADDR_WIDTH - 1:0] waddr,
    input wire [DATA_WIDTH - 1:0] din,
    input wire [0:0] we
    );

    reg [DATA_WIDTH - 1:0] data [RAM_ROWS - 1:0];

    always @(posedge clk) begin
        if (we) begin
            data[waddr] <= din;
        end
    end

    generate if (REGISTER_OUTPUT) begin
        always @(posedge clk) begin
            dout <= data[raddr];
        end
    end else begin
        always @* begin
            dout = data[raddr];
        end
    end endgenerate

endmodule

cocotb/fifo_lookahead/fifo.v
// Automatically generated by PRGA's RTL generator
module fifo #(
    parameter DEPTH_LOG2 = 3,
    parameter DATA_WIDTH = 32,
    parameter LOOKAHEAD = 1,
    parameter ALLOW_RAM_UNREGISTERED_OUTPUT = 0
) (
    input wire [0:0] clk,
    input  [0:0] rst,

    output wire [0:0] full,
    input wire [0:0] wr,
    input wire [DATA_WIDTH - 1:0] din,

    output wire [0:0] empty,
    input wire [0:0] rd,
    output wire [DATA_WIDTH - 1:0] dout,

    // Test variables
    input wire [0:0] test_clk 
    );


    initial begin
        $dumpfile("dump.vcd");
        $dumpvars(1,fifo);
    end


    // register reset signal for timing purpose
    reg rst_f;
    always @(posedge clk) begin
        rst_f <= rst;
    end

    localparam FIFO_DEPTH = 1 << DEPTH_LOG2;

    reg [DEPTH_LOG2:0] wr_ptr, rd_ptr;
    wire rd_internal;
    wire [DATA_WIDTH - 1:0] ram_dout;

    ram_1r1w #(
        .DATA_WIDTH         (DATA_WIDTH)
        ,.ADDR_WIDTH        (DEPTH_LOG2)
        ,.RAM_ROWS          (FIFO_DEPTH)
        ,.REGISTER_OUTPUT   (!ALLOW_RAM_UNREGISTERED_OUTPUT || !LOOKAHEAD)
    ) ram (
        .clk                (clk)
        ,.raddr             (rd_ptr)
        ,.dout              (ram_dout)
        ,.waddr             (wr_ptr)
        ,.din               (din)
        ,.we                (!full && wr)
        );

    always @(posedge clk) begin
        if (rst) begin
            wr_ptr <= 'b0;
            rd_ptr <= 'b0;
        end else begin
            if (~full && wr) begin
                wr_ptr <= wr_ptr + 1;
            end

            if (~empty && rd_internal) begin
                rd_ptr <= rd_ptr + 1;
            end
        end
    end

    assign full = rst_f || rd_ptr == {~wr_ptr[DEPTH_LOG2], wr_ptr[0 +: DEPTH_LOG2]};

    generate if (LOOKAHEAD && !ALLOW_RAM_UNREGISTERED_OUTPUT) begin
        fifo_lookahead_buffer #(
            .DATA_WIDTH             (DATA_WIDTH)
            ,.REVERSED              (0)
        ) buffer (
            .clk                    (clk)
            ,.rst                   (rst)
            ,.empty_i               (rst_f || rd_ptr == wr_ptr)
            ,.rd_i                  (rd_internal)
            ,.dout_i                (ram_dout)
            ,.empty                 (empty)
            ,.rd                    (rd)
            ,.dout                  (dout)
            );
    end else begin
        assign rd_internal = rd;
        assign dout = ram_dout;
        assign empty = rst_f || (rd_ptr == wr_ptr);
    end endgenerate

endmodule

cocotb/fifo_non_lookahead_to_lookahead/fifo_wrapper.v
 module fifo_wrapper (
    input clk,
    input rst,
    output full,
    input  wr,
    input [DATA_WIDTH - 1:0] din,
    output empty,
    input rd,
    output [DATA_WIDTH - 1:0] dout,
     output [DATA_WIDTH - 1:0] _dout,
     output _empty, _rd
);

    localparam DATA_WIDTH = 32;


//    wire [DATA_WIDTH - 1:0] _dout;



    fifo #(
        .DATA_WIDTH                     (DATA_WIDTH)
        ,.LOOKAHEAD                     (0)
    ) D (
        .clk        (clk)
        ,.rst       (rst)
        ,.full      (full)
        ,.wr        (wr)
        ,.din       (din)
        ,.empty     (_empty)
        ,.rd        (_rd)
        ,.dout      (_dout)
        );

    fifo_lookahead_buffer #(
        .DATA_WIDTH                     (DATA_WIDTH)
        ,.REVERSED                      (0)
    ) Buffer (
        .clk        (clk)
        ,.rst       (rst)
        ,.empty_i   (_empty)
        ,.rd_i      (_rd)
        ,.dout_i    (_dout)
        ,.empty     (empty)
        ,.rd        (rd)
        ,.dout      (dout)
        );

endmodule

cocotb/fifo_non_lookahead_to_lookahead/fifo_tb.v
module fifo_tb();
   localparam DATA_WIDTH = 32;
    // Inputs
    reg [0:0] clk;
    reg [0:0] rst;
    reg [0:0] wr;
    reg [31:0] din;
    reg [0:0] rd;

    // Outputs
    wire [0:0] full;
    wire [0:0] empty;
    wire [31:0] dout,_dout;
    wire _empty, _rd;
     
   reg [DATA_WIDTH - 1:0] src [0:1023];
    
     reg valid;
     reg error;
    integer wr_cnt; 
    integer rd_cnt;
    // Instantiate the Unit Under Test (UUT)
    fifo_wrapper uut (
        .clk(clk),
        .rst(rst),
        .full(full),
        .wr(wr),
        .din(din), 
        .empty(empty), 
        .rd(rd), 
        .dout(dout),
        ._dout(_dout),
        ._rd(_rd),
        ._empty(_empty)
    ); 

    initial begin
        $dumpfile("dump.vcd");
        $dumpvars(1,fifo_tb);
        // Initialize Inputs
        clk = 0;
        rst = 1'b1;
        wr = 1;
        din = 0;
        rd = 0;
        src[0] = 'h5A;
        src[1] = 'hF6;
        src[2] = 'h09;
        src[3] = 'hC4;
        src[4] = 'h81;
        src[5] = 'hE2;
        src[6] = 'hA0;
        src[7] = 'h7A;
          clk =0;
           $display("src[0] = %d", src[0]); 
           $display("src[1] = %d", src[1]);
           $display("src[2] = %d", src[2]);
           $display("src[3] = %d", src[3]);
           $display("src[4] = %d", src[4]);           
           $display("src[5] = %d", src[5]);
                         $display("src[6] = %d", src[6]);
                                        $display("src[7] = %d", src[7]);
        // Wait 100 ns for global reset to finish
        #10;
        rst = 1'b0;        
        // Add stimulus here

               #100000;
        $display("[TIMEOUT]");
        $finish;
 
    end
     always #5 clk = ~clk;
      always @(*) begin
      din <= src[wr_cnt];
       wr <= (src[wr_cnt] !== {DATA_WIDTH{1'bx}});
      end
         always @(posedge clk) begin
        if (rst) begin
            wr_cnt <= 0;
            rd_cnt <= 0;
            valid <= 'b0;
            rd <= 'b0;
            error <= 'b0;
        end else begin
            if (!full && src[wr_cnt] !== {DATA_WIDTH{1'bx}}) begin
                wr_cnt <= wr_cnt + 1;
            end

            valid <= !empty && rd;

            if (valid) begin
                if (src[rd_cnt] !== dout) begin
                                    error <= 'b1;
                                     $display("s time is ",$stime); 
                           $display("[ERROR] output No. %d %d != %d", rd_cnt, dout, src[rd_cnt]);
                          end
                rd_cnt <= rd_cnt + 1;
            end

            rd = $urandom_range(0,1) ;

            if (src[rd_cnt] === {DATA_WIDTH{1'bx}}) begin
                if (error) begin
                    $display("[FAIL]");
                end else begin
                    $display("[PASS]");
                end
                $finish;
            end
        end
    end
endmodule

cocotb/fifo_non_lookahead_to_lookahead/dump.vcd
$date
	Mon May 18 16:35:13 2020
$end
$version
	Icarus Verilog
$end
$timescale
	1s
$end
$scope module fifo_tb $end
$var wire 1 ! full $end
$var wire 1 " empty $end
$var wire 32 # dout [31:0] $end
$var wire 1 $ _rd $end
$var wire 1 % _empty $end
$var wire 32 & _dout [31:0] $end
$var reg 1 ' clk $end
$var reg 32 ( din [31:0] $end
$var reg 1 ) error $end
$var reg 1 * rd $end
$var reg 1 + rst $end
$var reg 1 , valid $end
$var reg 1 - wr $end
$var integer 32 . rd_cnt [31:0] $end
$var integer 32 / wr_cnt [31:0] $end
$upscope $end
$enddefinitions $end
#0
$dumpvars
bx /
bx .
0-
x,
1+
0*
x)
bx (
0'
bx &
x%
0$
bx #
x"
x!
$end
#5
1-
b1011010 (
1"
1!
1%
0)
0,
b0 .
b0 /
1'
#10
0'
0+
#15
0!
1$
1*
1'
#20
0'
#25
b11110110 (
b1 /
0$
0*
1'
#30
0'
#35
b1001 (
b1011010 &
0"
b10 /
0%
1'
#40
0'
#45
b11000100 (
b1011010 #
b11 /
1'
#50
0'
#55
b10000001 (
b100 /
1$
1*
1'
#60
0'
#65
b11100010 (
1,
b101 /
1'
#70
0'
#75
b10100000 (
b11110110 &
b1 .
b110 /
0$
0*
1'
#80
0'
#85
b1111010 (
b11110110 #
b10 .
1)
0,
b111 /
1'
#90
0'
#95
0-
bx (
b1000 /
1$
1*
1'
#100
0'
#105
b1001 &
1,
1'
#110
0'
#115
b11000100 &
b11 .
b1001 #
1'
#120
0'
#125
b10000001 &
b11000100 #
b100 .
1'
#130
0'
#135
b11100010 &
b101 .
b10000001 #
1'
#140
0'
#145
b10100000 &
b11100010 #
b110 .
1'
#150
0'
#155
b1111010 &
b111 .
b10100000 #
1'
#160
0'
#165
1"
1%
b1111010 #
b1000 .
0$
0*
1'
#170
0'
#175
b11110110 &
0"
b1001 .
0,
0%
1'
