cocotb/fifo/prga_fifo_lookahead_buffer.v
// Automatically generated by PRGA's RTL generator
//
// Convert a non-lookahead FIFO to a lookahead FIFO if REVERSED is 0
// or, convert a lookahead FIFO to a non-lookahead FIFO if REVERSED is 1
module prga_fifo_lookahead_buffer #(
    parameter DATA_WIDTH = 32,
    parameter REVERSED = 0
) (
    input wire [0:0] clk,
    input  [0:0] rst,

    input wire [0:0] empty_i,
    output reg [0:0] rd_i,
    input wire [DATA_WIDTH - 1:0] dout_i,

    output reg [0:0] empty,
    input wire [0:0] rd,
    output reg [DATA_WIDTH - 1:0] dout
    );

    generate if (REVERSED) begin
        always @(posedge clk) begin
            dout <= dout_i;
        end

        always @* begin
            empty = empty_i;
            rd_i = rd;
        end
    end else begin
        reg [DATA_WIDTH - 1:0] dout_i_f;
        reg dout_i_valid;

        always @(posedge clk) begin
            if (rst) begin
                empty <= 'b1;
                dout_i_valid <= 'b0;
            end else begin
                if (~empty_i && rd_i) begin
                    empty <= 'b0;
                end else if (rd) begin
                    empty <= 'b1;
                end

                dout_i_valid <= ~empty_i && rd_i;
            end
        end

        always @(posedge clk) begin
            if (dout_i_valid) begin
                dout_i_f <= dout_i;
            end
        end

        always @* begin
            rd_i = empty || rd;
            dout = dout_i_valid ? dout_i : dout_i_f;
        end
    end endgenerate

endmodule

cocotb/fifo/iverilog/prga_ram_1r1w.v
// Automatically generated by PRGA's RTL generator
module prga_ram_1r1w #(
    parameter DATA_WIDTH = 32,
    parameter ADDR_WIDTH = 6,
    parameter RAM_ROWS = 64,
    parameter REGISTER_OUTPUT = 1
) (
    input wire [0:0] clk,

    input wire [ADDR_WIDTH - 1:0] raddr,
    output reg [DATA_WIDTH - 1:0] dout,

    input wire [ADDR_WIDTH - 1:0] waddr,
    input wire [DATA_WIDTH - 1:0] din,
    input wire [0:0] we
    );

    reg [DATA_WIDTH - 1:0] data [RAM_ROWS - 1:0];

    always @(posedge clk) begin
        if (we) begin
            data[waddr] <= din;
        end
    end

    generate if (REGISTER_OUTPUT) begin
        always @(posedge clk) begin
            dout <= data[raddr];
        end
    end else begin
        always @* begin
            dout = data[raddr];
        end
    end endgenerate

endmodule

cocotb/fifo/prga_fifo.v

// Automatically generated by PRGA's RTL generator
module prga_fifo #(
    parameter DEPTH_LOG2 = 1,
    parameter DATA_WIDTH = 32,
    parameter LOOKAHEAD = 0,
    parameter ALLOW_RAM_UNREGISTERED_OUTPUT = 0
) (
    input wire [0:0] clk,
    input  [0:0] rst,

    output wire [0:0] full,
    input wire [0:0] wr,
    input wire [DATA_WIDTH - 1:0] din,

    output wire [0:0] empty,
    input wire [0:0] rd,
    output wire [DATA_WIDTH - 1:0] dout
    );


    // register reset signal for timing purpose
    reg rst_f;
    always @(posedge clk) begin
        rst_f <= rst;
    end

    localparam FIFO_DEPTH = 1 << DEPTH_LOG2;

    reg [DEPTH_LOG2:0] wr_ptr, rd_ptr;
    wire rd_internal;
    wire [DATA_WIDTH - 1:0] ram_dout;

    prga_ram_1r1w #(
        .DATA_WIDTH         (DATA_WIDTH)
        ,.ADDR_WIDTH        (DEPTH_LOG2)
        ,.RAM_ROWS          (FIFO_DEPTH)
        ,.REGISTER_OUTPUT   (!ALLOW_RAM_UNREGISTERED_OUTPUT || !LOOKAHEAD)
    ) ram (
        .clk                (clk)
        ,.raddr             (rd_ptr)
        ,.dout              (ram_dout)
        ,.waddr             (wr_ptr)
        ,.din               (din)
        ,.we                (!full && wr)
        );

    always @(posedge clk) begin
        if (rst) begin
            wr_ptr <= 'b0;
            rd_ptr <= 'b0;
        end else begin
            if (~full && wr) begin
                wr_ptr <= wr_ptr + 1;
            end

            if (~empty && rd_internal) begin
                rd_ptr <= rd_ptr + 1;
            end
        end
    end

    assign full = rst_f || rd_ptr == {~wr_ptr[DEPTH_LOG2], wr_ptr[0 +: DEPTH_LOG2]};

    generate if (LOOKAHEAD && !ALLOW_RAM_UNREGISTERED_OUTPUT) begin
        prga_fifo_lookahead_buffer #(
            .DATA_WIDTH             (DATA_WIDTH)
            ,.REVERSED              (0)
        ) buffer (
            .clk                    (clk)
            ,.rst                   (rst)
            ,.empty_i               (rst_f || rd_ptr == wr_ptr)
            ,.rd_i                  (rd_internal)
            ,.dout_i                (ram_dout)
            ,.empty                 (empty)
            ,.rd                    (rd)
            ,.dout                  (dout)
            );
    end else begin
        assign rd_internal = rd;
        assign dout = ram_dout;
        assign empty = rst_f || rd_ptr == wr_ptr;
    end endgenerate

endmodule

cocotb/fifo/prga_fifo_tb_wrapper.v
module prga_fifo_tb_wrapper ();

    localparam DATA_WIDTH = 8;

    input clk, rst;

    input [DATA_WIDTH - 1:0] src [0:1023];

    // initial begin
      
    //     src[0] = 'h5A;
    //     src[1] = 'hF6;
    //     src[2] = 'h09;
    //     src[3] = 'hC4;
    //     src[4] = 'h81;
    //     src[5] = 'hE2;
    //     src[6] = 'hA0;
    //     src[7] = 'h7A;
    // end

    // A: non-lookahead
    // B: lookahead converted to non-lookahead
    // C: lookahead
    // D: non-lookahead converted to lookahead

    output A_full, A_empty, B_full, B_empty, C_full, C_empty, D_full, D_empty;
    output [DATA_WIDTH - 1:0] A_dout, B_dout, C_dout, D_dout;
    input A_valid, A_rd, B_valid, B_rd, C_rd, D_rd;
    input A_wr_cnt, B_wr_cnt, C_wr_cnt, D_wr_cnt;
    input A_rd_cnt, B_rd_cnt, C_rd_cnt, D_rd_cnt;
    output _B_empty, _B_rd, _D_empty, _D_rd;
    output [DATA_WIDTH - 1:0] _B_dout, _D_dout;

    initial begin
        $dumpfile("test.vcd");
        $dumpvars(1,prga_fifo_tb_wrapper);
    end
    prga_fifo #(
        .DATA_WIDTH                     (DATA_WIDTH)
        ,.LOOKAHEAD                     (0)
    ) A (
        .clk        (clk)
        ,.rst       (rst)
        ,.full      (A_full)
        ,.wr        (src[A_wr_cnt] !== {DATA_WIDTH{1'bx}})
        ,.din       (src[A_wr_cnt])
        ,.empty     (A_empty)
        ,.rd        (A_rd)
        ,.dout      (A_dout)
        );

    prga_fifo #(
        .DATA_WIDTH                     (DATA_WIDTH)
        ,.LOOKAHEAD                     (1)
    ) B (
        .clk        (clk)
        ,.rst       (rst)
        ,.full      (B_full)
        ,.wr        (src[B_wr_cnt] !== {DATA_WIDTH{1'bx}})
        ,.din       (src[B_wr_cnt])
        ,.empty     (_B_empty)
        ,.rd        (_B_rd)
        ,.dout      (_B_dout)
        );

    prga_fifo_lookahead_buffer #(
        .DATA_WIDTH                     (DATA_WIDTH)
        ,.REVERSED                      (1)
    ) B_buffer (
        .clk        (clk)
        ,.rst       (rst)
        ,.empty_i   (_B_empty)
        ,.rd_i      (_B_rd)
        ,.dout_i    (_B_dout)
        ,.empty     (B_empty)
        ,.rd        (B_rd)
        ,.dout      (B_dout)
        );

    prga_fifo #(
        .DATA_WIDTH                     (DATA_WIDTH)
        ,.LOOKAHEAD                     (1)
    ) C (
        .clk        (clk)
        ,.rst       (rst)
        ,.full      (C_full)
        ,.wr        (src[C_wr_cnt] !== {DATA_WIDTH{1'bx}})
        ,.din       (src[C_wr_cnt])
        ,.empty     (C_empty)
        ,.rd        (C_rd)
        ,.dout      (C_dout)
        );

    prga_fifo #(
        .DATA_WIDTH                     (DATA_WIDTH)
        ,.LOOKAHEAD                     (0)
    ) D (
        .clk        (clk)
        ,.rst       (rst)
        ,.full      (D_full)
        ,.wr        (src[D_wr_cnt] !== {DATA_WIDTH{1'bx}})
        ,.din       (src[D_wr_cnt])
        ,.empty     (_D_empty)
        ,.rd        (_D_rd)
        ,.dout      (_D_dout)
        );

    prga_fifo_lookahead_buffer #(
        .DATA_WIDTH                     (DATA_WIDTH)
        ,.REVERSED                      (0)
    ) D_buffer (
        .clk        (clk)
        ,.rst       (rst)
        ,.empty_i   (_D_empty)
        ,.rd_i      (_D_rd)
        ,.dout_i    (_D_dout)
        ,.empty     (D_empty)
        ,.rd        (D_rd)
        ,.dout      (D_dout)
        );

endmodule

cocotb/fifo/test.vcd
$date
	Mon May 11 15:54:58 2020
$end
$version
	Icarus Verilog
$end
$timescale
	1s
$end
$scope module prga_fifo_tb_wrapper $end
$var wire 1 ! A_rd $end
$var wire 1 " A_rd_cnt $end
$var wire 1 # A_valid $end
$var wire 1 $ A_wr_cnt $end
$var wire 1 % B_rd $end
$var wire 1 & B_rd_cnt $end
$var wire 1 ' B_valid $end
$var wire 1 ( B_wr_cnt $end
$var wire 1 ) C_rd $end
$var wire 1 * C_rd_cnt $end
$var wire 1 + C_wr_cnt $end
$var wire 1 , D_rd $end
$var wire 1 - D_rd_cnt $end
$var wire 1 . D_wr_cnt $end
$var wire 1 / clk $end
$var wire 1 0 rst $end
$var wire 8 1 src [7:0] $end
$var wire 1 2 _D_rd $end
$var wire 1 3 _D_empty $end
$var wire 8 4 _D_dout [7:0] $end
$var wire 1 5 _B_rd $end
$var wire 1 6 _B_empty $end
$var wire 8 7 _B_dout [7:0] $end
$var wire 1 8 D_full $end
$var wire 1 9 D_empty $end
$var wire 8 : D_dout [7:0] $end
$var wire 1 ; C_full $end
$var wire 1 < C_empty $end
$var wire 8 = C_dout [7:0] $end
$var wire 1 > B_full $end
$var wire 1 ? B_empty $end
$var wire 8 @ B_dout [7:0] $end
$var wire 1 A A_full $end
$var wire 1 B A_empty $end
$var wire 8 C A_dout [7:0] $end
$upscope $end
$enddefinitions $end
#0
$dumpvars
bx C
xB
xA
bx @
x?
x>
bx =
x<
x;
bx :
x9
x8
bx 7
x6
z5
bx 4
x3
x2
bz 1
z0
1/
z.
z-
z,
z+
z*
z)
z(
z'
z&
z%
z$
z#
z"
z!
$end
#5
0/
#10
1/
#15
0/
#20
1/
#25
0/
#30
1/
#35
0/
#40
1/
#45
0/
#50
1/
#55
0/
#60
1/
#65
0/
#70
1/
#75
0/
#80
1/
#85
0/
#90
1/
#95
0/
#100
1/
#105
0/
#110
1/
#115
0/
#120
1/
#125
0/
#130
1/
#135
0/
#140
1/
#145
0/
#150
1/
#155
0/
#160
1/
#165
0/
#170
1/
#175
0/
#180
1/
#185
0/
#190
1/
#195
0/
#200
1/
#205
0/
#210
1/
#215
0/
#220
1/
#225
0/
#230
1/
#235
0/
#240
1/
#245
0/
#250
1/
#255
0/
#260
1/
#265
0/
#270
1/
#275
0/
#280
1/
#285
0/
#290
1/
#295
0/
#300
1/
#305
0/
#310
1/
#315
0/
#320
1/
#325
0/
#330
1/
#335
0/
#340
1/
#345
0/
#350
1/
#355
0/
#360
1/
#365
0/
#370
1/
#375
0/
#380
1/
#385
0/
#390
1/
#395
0/
#400
1/
#405
0/
#410
1/
#415
0/
#420
1/
#425
0/
#430
1/
#435
0/
#440
1/
#445
0/
#450
1/
#455
0/
#460
1/
#465
0/
#470
1/
#475
0/
#480
1/
#485
0/
#490
1/
#495
0/
#500
1/
#505
0/
#510
1/
#515
0/
#520
1/
#525
0/
#530
1/
#535
0/
#540
1/
#545
0/
#550
1/
#555
0/
#560
1/
#565
0/
#570
1/
#575
0/
#580
1/
#585
0/
#590
1/
#595
0/
#600
1/
#605
0/
#610
1/
#615
0/
#620
1/
#625
0/
#630
1/
#635
0/
#640
1/
#645
0/
#650
1/
#655
0/
#660
1/
#665
0/
#670
1/
#675
0/
#680
1/
#685
0/
#690
1/
#695
0/
#700
1/
#705
0/
#710
1/
#715
0/
#720
1/
#725
0/
#730
1/
#735
0/
#740
1/
#745
0/
#750
1/
#755
0/
#760
1/
#765
0/
#770
1/
#775
0/
#780
1/
#785
0/
#790
1/
#795
0/
#800
1/
#805
0/
#810
1/
#815
0/
#820
1/
#825
0/
#830
1/
#835
0/
#840
1/
#845
0/
#850
1/
#855
0/
#860
1/
#865
0/
#870
1/
#875
0/
#880
1/
#885
0/
#890
1/
#895
0/
#900
1/
#905
0/
#910
1/
#915
0/
#920
1/
#925
0/
#930
1/
#935
0/
#940
1/
#945
0/
#950
1/
#955
0/
#960
1/
#965
0/
#970
1/
#975
0/
#980
1/
#985
0/
#990
1/
#995
0/
#1000
00
1/
#1003
10
#1005
0/
#1010
12
13
18
1;
1>
1?
1B
1A
19
1<
16
1/
#1013
00
#1015
0/
#1020
0A
0>
0;
08
1/
#1025
0/
#1030
03
0B
1/
#1035
0/
#1040
1A
1>
1;
0?
b0x 7
b0x =
b0x :
x2
b0x C
06
0<
b0x 4
09
1/
#1045
0/
#1050
18
b0x @
1/
