cocotb/ram/ram.v
// Code your design here
/* 
 * Random Access Memory (RAM) with
 * 1 read port and 1 write port
 */
module ram (clk_write, address_write,
  data_write, write_enable,
  clk_read, address_read, data_read);
  
  parameter D_WIDTH = 16;
  parameter A_WIDTH = 5;

  // Write port
  input                clk_write;
  input  [A_WIDTH-1:0] address_write;
  input  [D_WIDTH-1:0] data_write;
  input                write_enable;

  // Read port
  input                clk_read;
  input  [A_WIDTH-1:0] address_read;
  output [D_WIDTH-1:0] data_read;
  
  reg    [D_WIDTH-1:0] data_read;
  
  // Memory as multi-dimensional array
  reg [D_WIDTH-1:0] memory [0:2**A_WIDTH-1];
    initial begin
        $dumpfile("test.vcd");
        $dumpvars(1,ram);
    end
  // Write data to memory
  always @(posedge clk_write) begin
    if (write_enable) begin
      memory[address_write] <= data_write;
    end
  end

  // Read data from memory
  always @(posedge clk_read) begin
    data_read <= memory[address_read];
  end

endmodule

cocotb/ram/test.vcd
$date
	Sun May 10 16:12:15 2020
$end
$version
	Icarus Verilog
$end
$timescale
	1s
$end
$scope module ram $end
$var wire 5 ! address_read [4:0] $end
$var wire 5 " address_write [4:0] $end
$var wire 1 # clk_read $end
$var wire 1 $ clk_write $end
$var wire 16 % data_write [15:0] $end
$var wire 1 & write_enable $end
$var reg 16 ' data_read [15:0] $end
$upscope $end
$enddefinitions $end
#0
$dumpvars
bx '
1&
b1010011001010110 %
1$
1#
b0 "
bz !
$end
#1600
0$
#2500
0#
#3200
0&
1$
#4800
0$
#5000
1#
#6400
b1 "
b110111101 %
1&
1$
#7500
0#
#8000
0$
#9600
0&
1$
#10000
1#
#11200
0$
#12500
0#
#12800
b10 "
b10100101100 %
1&
1$
#14400
0$
#15000
1#
#16000
0&
1$
#17500
0#
#17600
0$
#19200
b11 "
b1010100011010101 %
1&
1$
#20000
1#
#20800
0$
#22400
0&
1$
#22500
0#
#24000
0$
#25000
1#
#25600
b100 "
b1011000100010001 %
1&
1$
#27200
0$
#27500
0#
#28800
0&
1$
#30000
1#
#30400
0$
#32000
b101 "
b111111000000100 %
1&
1$
#32500
0#
#33600
0$
#35000
1#
#35200
0&
1$
#36800
0$
#37500
0#
#38400
b110 "
b1101101000101 %
1&
1$
#40000
1#
0$
#41600
0&
1$
#42500
0#
#43200
0$
#44800
b111 "
b1101100110011111 %
1&
1$
#45000
1#
#46400
0$
#47500
0#
#48000
0&
1$
#49600
0$
#50000
1#
#51200
b1000 "
b1001010000110010 %
1&
1$
#52500
0#
#52800
0$
#54400
0&
1$
#55000
1#
#56000
0$
#57500
0#
#57600
b1001 "
b1010101001011010 %
1&
1$
#59200
0$
#60000
1#
#60800
0&
1$
#62400
0$
#62500
0#
#64000
b1010 "
b1000010010000101 %
1&
1$
#65000
1#
#65600
0$
#67200
0&
1$
#67500
0#
#68800
0$
#70000
1#
#70400
b1011 "
b1001011110000011 %
1&
1$
#72000
0$
#72500
0#
#73600
0&
1$
#75000
1#
#75200
0$
#76800
b1100 "
b1101100110001010 %
1&
1$
#77500
0#
#78400
0$
#80000
0&
1#
1$
#81600
0$
#82500
0#
#83200
b1101 "
b1010101000111 %
1&
1$
#84800
0$
#85000
1#
#86400
0&
1$
#87500
0#
#88000
0$
#89600
b1110 "
b1000101101000010 %
1&
1$
#90000
1#
#91200
0$
#92500
0#
#92800
0&
1$
#94400
0$
#95000
1#
#96000
b1111 "
b1110101011111110 %
1&
1$
#97500
0#
#97600
0$
#99200
0&
1$
#100000
1#
#100800
0$
#102400
b10000 "
b101001011101110 %
1&
1$
#102500
0#
#104000
0$
#105000
1#
#105600
0&
1$
#107200
0$
#107500
0#
#108800
b10001 "
b1110000001011110 %
1&
1$
#110000
1#
#110400
0$
#112000
0&
1$
#112500
0#
#113600
0$
#115000
1#
#115200
b10010 "
b111101110000101 %
1&
1$
#116800
0$
#117500
0#
#118400
0&
1$
#120000
1#
0$
#121600
b10011 "
b1011001101010000 %
1&
1$
#122500
0#
#123200
0$
#124800
0&
1$
#125000
1#
#126400
0$
#127500
0#
#128000
b10100 "
b1000110100001011 %
1&
1$
#129600
0$
#130000
1#
#131200
0&
1$
#132500
0#
#132800
0$
#134400
b10101 "
b1011110011001001 %
1&
1$
#135000
1#
#136000
0$
#137500
0#
#137600
0&
1$
#139200
0$
#140000
1#
#140800
b10110 "
b101000001101100 %
1&
1$
#142400
0$
#142500
0#
#144000
0&
1$
#145000
1#
#145600
0$
#147200
b10111 "
b1010000001000010 %
1&
1$
#147500
0#
#148800
0$
#150000
1#
#150400
0&
1$
#152000
0$
#152500
0#
#153600
b11000 "
b110110010110011 %
1&
1$
#155000
1#
#155200
0$
#156800
0&
1$
#157500
0#
#158400
0$
#160000
b11001 "
b111011011000011 %
1&
1#
1$
#161600
0$
#162500
0#
#163200
0&
1$
#164800
0$
#165000
1#
#166400
b11010 "
b1100011111000101 %
1&
1$
#167500
0#
#168000
0$
#169600
0&
1$
#170000
1#
#171200
0$
#172500
0#
#172800
b11011 "
b10001101011111 %
1&
1$
#174400
0$
#175000
1#
#176000
0&
1$
#177500
0#
#177600
0$
#179200
b11100 "
b1101001011001011 %
1&
1$
#180000
1#
#180800
0$
#182400
0&
1$
#182500
0#
#184000
0$
#185000
1#
#185600
b11101 "
b11111001101011 %
1&
1$
#187200
0$
#187500
0#
#188800
0&
1$
#190000
1#
#190400
0$
#192000
b11110 "
b100101001000100 %
1&
1$
#192500
0#
#193600
0$
#195000
1#
#195200
0&
1$
#196800
0$
#197500
0#
#198400
b11111 "
b1111011000000101 %
1&
1$
#200000
1#
0$
#201600
0&
1$
#202500
0#
#203200
0$
#204800
1$
#205000
b0 !
1#
#206400
0$
#207500
0#
#208000
1$
#209600
0$
#210000
b1010011001010110 '
1#
#211200
1$
#212500
0#
#212800
0$
#214400
1$
#215000
b1 !
1#
#216000
0$
#217500
0#
#217600
1$
#219200
0$
#220000
b110111101 '
1#
#220800
1$
#222400
0$
#222500
0#
#224000
1$
#225000
b10 !
1#
#225600
0$
#227200
1$
#227500
0#
#228800
0$
#230000
b10100101100 '
1#
#230400
1$
#232000
0$
#232500
0#
#233600
1$
#235000
b11 !
1#
#235200
0$
#236800
1$
#237500
0#
#238400
0$
#240000
b1010100011010101 '
1#
1$
#241600
0$
#242500
0#
#243200
1$
#244800
0$
#245000
b100 !
1#
#246400
1$
#247500
0#
#248000
0$
#249600
1$
#250000
b1011000100010001 '
1#
#251200
0$
#252500
0#
#252800
1$
#254400
0$
#255000
b101 !
1#
#256000
1$
#257500
0#
#257600
0$
#259200
1$
#260000
b111111000000100 '
1#
#260800
0$
#262400
1$
#262500
0#
#264000
0$
#265000
b110 !
1#
#265600
1$
#267200
0$
#267500
0#
#268800
1$
#270000
b1101101000101 '
1#
#270400
0$
#272000
1$
#272500
0#
#273600
0$
#275000
b111 !
1#
#275200
1$
#276800
0$
#277500
0#
#278400
1$
#280000
b1101100110011111 '
1#
0$
#281600
1$
#282500
0#
#283200
0$
#284800
1$
#285000
b1000 !
1#
#286400
0$
#287500
0#
#288000
1$
#289600
0$
#290000
b1001010000110010 '
1#
#291200
1$
#292500
0#
#292800
0$
#294400
1$
#295000
b1001 !
1#
#296000
0$
#297500
0#
#297600
1$
#299200
0$
#300000
b1010101001011010 '
1#
#300800
1$
#302400
0$
#302500
0#
#304000
1$
#305000
b1010 !
1#
#305600
0$
#307200
1$
#307500
0#
#308800
0$
#310000
b1000010010000101 '
1#
#310400
1$
#312000
0$
#312500
0#
#313600
1$
#315000
b1011 !
1#
#315200
0$
#316800
1$
#317500
0#
#318400
0$
#320000
b1001011110000011 '
1#
1$
#321600
0$
#322500
0#
#323200
1$
#324800
0$
#325000
b1100 !
1#
#326400
1$
#327500
0#
#328000
0$
#329600
1$
#330000
b1101100110001010 '
1#
#331200
0$
#332500
0#
#332800
1$
#334400
0$
#335000
b1101 !
1#
#336000
1$
#337500
0#
#337600
0$
#339200
1$
#340000
b1010101000111 '
1#
#340800
0$
#342400
1$
#342500
0#
#344000
0$
#345000
b1110 !
1#
#345600
1$
#347200
0$
#347500
0#
#348800
1$
#350000
b1000101101000010 '
1#
#350400
0$
#352000
1$
#352500
0#
#353600
0$
#355000
b1111 !
1#
#355200
1$
#356800
0$
#357500
0#
#358400
1$
#360000
b1110101011111110 '
1#
0$
#361600
1$
#362500
0#
#363200
0$
#364800
1$
#365000
b10000 !
1#
#366400
0$
#367500
0#
#368000
1$
#369600
0$
#370000
b101001011101110 '
1#
#371200
1$
#372500
0#
#372800
0$
#374400
1$
#375000
b10001 !
1#
#376000
0$
#377500
0#
#377600
1$
#379200
0$
#380000
b1110000001011110 '
1#
#380800
1$
#382400
0$
#382500
0#
#384000
1$
#385000
b10010 !
1#
#385600
0$
#387200
1$
#387500
0#
#388800
0$
#390000
b111101110000101 '
1#
#390400
1$
#392000
0$
#392500
0#
#393600
1$
#395000
b10011 !
1#
#395200
0$
#396800
1$
#397500
0#
#398400
0$
#400000
b1011001101010000 '
1#
1$
#401600
0$
#402500
0#
#403200
1$
#404800
0$
#405000
b10100 !
1#
#406400
1$
#407500
0#
#408000
0$
#409600
1$
#410000
b1000110100001011 '
1#
#411200
0$
#412500
0#
#412800
1$
#414400
0$
#415000
b10101 !
1#
#416000
1$
#417500
0#
#417600
0$
#419200
1$
#420000
b1011110011001001 '
1#
#420800
0$
#422400
1$
#422500
0#
#424000
0$
#425000
b10110 !
1#
#425600
1$
#427200
0$
#427500
0#
#428800
1$
#430000
b101000001101100 '
1#
#430400
0$
#432000
1$
#432500
0#
#433600
0$
#435000
b10111 !
1#
#435200
1$
#436800
0$
#437500
0#
#438400
1$
#440000
b1010000001000010 '
1#
0$
#441600
1$
#442500
0#
#443200
0$
#444800
1$
#445000
b11000 !
1#
#446400
0$
#447500
0#
#448000
1$
#449600
0$
#450000
b110110010110011 '
1#
#451200
1$
#452500
0#
#452800
0$
#454400
1$
#455000
b11001 !
1#
#456000
0$
#457500
0#
#457600
1$
#459200
0$
#460000
b111011011000011 '
1#
#460800
1$
#462400
0$
#462500
0#
#464000
1$
#465000
b11010 !
1#
#465600
0$
#467200
1$
#467500
0#
#468800
0$
#470000
b1100011111000101 '
1#
#470400
1$
#472000
0$
#472500
0#
#473600
1$
#475000
b11011 !
1#
#475200
0$
#476800
1$
#477500
0#
#478400
0$
#480000
b10001101011111 '
1#
1$
#481600
0$
#482500
0#
#483200
1$
#484800
0$
#485000
b11100 !
1#
#486400
1$
#487500
0#
#488000
0$
#489600
1$
#490000
b1101001011001011 '
1#
#491200
0$
#492500
0#
#492800
1$
#494400
0$
#495000
b11101 !
1#
#496000
1$
#497500
0#
#497600
0$
#499200
1$
#500000
b11111001101011 '
1#
#500800
0$
#502400
1$
#502500
0#
#504000
0$
#505000
b11110 !
1#
#505600
1$
#507200
0$
#507500
0#
#508800
1$
#510000
b100101001000100 '
1#
#510400
0$
#512000
1$
#512500
0#
#513600
0$
#515000
b11111 !
1#
#515200
1$
#516800
0$
#517500
0#
#518400
1$
#520000
b1111011000000101 '
1#
0$
